stability_ai/__init__.py
stability_ai/client.py
stability_ai/client_interface.py
stability_ai/util.py
stability_ai_sdk-0.0.1.dist-info/LICENSE
stability_ai_sdk-0.0.1.dist-info/METADATA
stability_ai_sdk-0.0.1.dist-info/WHEEL
stability_ai_sdk-0.0.1.dist-info/top_level.txt
stability_ai_sdk-0.0.1.dist-info/RECORD
