Metadata-Version: 2.1
Name: stability-ai-sdk
Version: 0.0.1
Summary: Python client for Stability AI API
Author: Jack Beoris
License: 
Project-URL: homepage, https://jackbeoris.com
Project-URL: repository, https://github.com/jbeoris/stability-ai-python-sdk
Requires-Python: >=3.8
License-File: LICENSE
Requires-Dist: python-dotenv~=1.0
Requires-Dist: requests~=2.32
Provides-Extra: dev
Requires-Dist: pytest; extra == "dev"
